HulianwangGongsiChangyongKuangjiaYuanmaShangxiFix1/README.md
HulianwangGongsiChangyongKuangjiaYuanmaShangxiFix1/__init__.py
HulianwangGongsiChangyongKuangjiaYuanmaShangxiFix1/__main__.py
HulianwangGongsiChangyongKuangjiaYuanmaShangxiFix1/file.epub
HulianwangGongsiChangyongKuangjiaYuanmaShangxiFix1/index.html
HulianwangGongsiChangyongKuangjiaYuanmaShangxiFix1/css/__init__.py
HulianwangGongsiChangyongKuangjiaYuanmaShangxiFix1/css/annotations.css
HulianwangGongsiChangyongKuangjiaYuanmaShangxiFix1/css/main.css
HulianwangGongsiChangyongKuangjiaYuanmaShangxiFix1/css/normalize.css
HulianwangGongsiChangyongKuangjiaYuanmaShangxiFix1/css/popup.css
HulianwangGongsiChangyongKuangjiaYuanmaShangxiFix1/font/__init__.py
HulianwangGongsiChangyongKuangjiaYuanmaShangxiFix1/font/fontello.eot
HulianwangGongsiChangyongKuangjiaYuanmaShangxiFix1/font/fontello.svg
HulianwangGongsiChangyongKuangjiaYuanmaShangxiFix1/font/fontello.ttf
HulianwangGongsiChangyongKuangjiaYuanmaShangxiFix1/font/fontello.woff
HulianwangGongsiChangyongKuangjiaYuanmaShangxiFix1/img/__init__.py
HulianwangGongsiChangyongKuangjiaYuanmaShangxiFix1/img/annotator-glyph-sprite.png
HulianwangGongsiChangyongKuangjiaYuanmaShangxiFix1/img/annotator-icon-sprite.png
HulianwangGongsiChangyongKuangjiaYuanmaShangxiFix1/img/apple-touch-icon.png
HulianwangGongsiChangyongKuangjiaYuanmaShangxiFix1/img/cancelfullscreen.png
HulianwangGongsiChangyongKuangjiaYuanmaShangxiFix1/img/close.png
HulianwangGongsiChangyongKuangjiaYuanmaShangxiFix1/img/fullscreen.png
HulianwangGongsiChangyongKuangjiaYuanmaShangxiFix1/img/loader.gif
HulianwangGongsiChangyongKuangjiaYuanmaShangxiFix1/img/menu-icon.png
HulianwangGongsiChangyongKuangjiaYuanmaShangxiFix1/img/save.png
HulianwangGongsiChangyongKuangjiaYuanmaShangxiFix1/img/saved.png
HulianwangGongsiChangyongKuangjiaYuanmaShangxiFix1/img/settings-s.png
HulianwangGongsiChangyongKuangjiaYuanmaShangxiFix1/img/settings.png
HulianwangGongsiChangyongKuangjiaYuanmaShangxiFix1/img/star.png
hulianwang_gongsi_changyong_kuangjia_yuanma_shangxi_fix1-2025.3.25.0.dist-info/METADATA
hulianwang_gongsi_changyong_kuangjia_yuanma_shangxi_fix1-2025.3.25.0.dist-info/WHEEL
hulianwang_gongsi_changyong_kuangjia_yuanma_shangxi_fix1-2025.3.25.0.dist-info/entry_points.txt
hulianwang_gongsi_changyong_kuangjia_yuanma_shangxi_fix1-2025.3.25.0.dist-info/top_level.txt
hulianwang_gongsi_changyong_kuangjia_yuanma_shangxi_fix1-2025.3.25.0.dist-info/RECORD
